{
  "status": "success",
  "log_file": "/home/arz2/PolyJarvis/data/PLA1/lammps/thermal/tg_sweep_r640/tg_sweep_r640.log",
  "output_dir": "/home/arz2/PolyJarvis/data/PLA1/raw/tg_r640",
  "Tg_K": 365.0,
  "Tg_alternative_K": 225.0,
  "r_squared": 0.9683,
  "fit_quality": "ACCEPTABLE",
  "fit_method": "hyperbola_curvefit",
  "transition_width_c_K": 0.1,
  "tg_uncertainty_K": 88.0,
  "binning_method": "plateau_detection",
  "fit_params": {
    "a_glassy": -0.0002754602102527482,
    "b_glassy": 1.3053477644075686,
    "a_rubbery": -0.00035043947638018446,
    "b_rubbery": 1.3327167898302132
  },
  "n_temperature_bins": 30,
  "n_plateau_bins": 30,
  "n_plateaus_skipped_drift": 6,
  "n_plateaus_low_n_eff": 11,
  "temp_range_K": [
    220.0,
    605.0
  ],
  "bins_csv": "/home/arz2/PolyJarvis/data/PLA1/raw/tg_r640/tg_density_bins.csv",
  "bins_csv_plateau": "/home/arz2/PolyJarvis/data/PLA1/raw/tg_r640/tg_density_bins_plateau.csv",
  "equilibration_fraction": 0.5,
  "temp_col": "Temp",
  "density_col": "Density",
  "slope_signs_valid": true,
  "slope_ordering_valid": true,
  "fit_warnings": [],
  "relaxation_metrics": [
    {
      "temperature": 605.0,
      "n_eff": 6.62,
      "tau_int_steps": 0.6,
      "relax_warning": false
    },
    {
      "temperature": 600.0,
      "n_eff": 8.57,
      "tau_int_steps": 0.5,
      "relax_warning": false
    },
    {
      "temperature": 595.0,
      "n_eff": 13.0,
      "tau_int_steps": 0.5,
      "relax_warning": false
    },
    {
      "temperature": 595.0,
      "n_eff": 3.0,
      "tau_int_steps": 0.5,
      "relax_warning": true
    },
    {
      "temperature": 575.0,
      "n_eff": 13.0,
      "tau_int_steps": 0.5,
      "relax_warning": false
    },
    {
      "temperature": 580.0,
      "n_eff": 5.0,
      "tau_int_steps": 0.5,
      "relax_warning": false
    },
    {
      "temperature": 580.0,
      "n_eff": 5.44,
      "tau_int_steps": 1.1,
      "relax_warning": false
    },
    {
      "temperature": 560.0,
      "n_eff": 16.05,
      "tau_int_steps": 0.5,
      "relax_warning": false
    },
    {
      "temperature": 560.0,
      "n_eff": 4.0,
      "tau_int_steps": 0.5,
      "relax_warning": true
    },
    {
      "temperature": 560.0,
      "n_eff": 9.0,
      "tau_int_steps": 0.5,
      "relax_warning": false
    },
    {
      "temperature": 565.0,
      "n_eff": 3.0,
      "tau_int_steps": 0.5,
      "relax_warning": true
    },
    {
      "temperature": 540.0,
      "n_eff": 3.78,
      "tau_int_steps": 0.9,
      "relax_warning": true
    },
    {
      "temperature": 540.0,
      "n_eff": 17.0,
      "tau_int_steps": 0.5,
      "relax_warning": false
    },
    {
      "temperature": 545.0,
      "n_eff": 4.0,
      "tau_int_steps": 0.5,
      "relax_warning": true
    },
    {
      "temperature": 535.0,
      "n_eff": 3.12,
      "tau_int_steps": 0.8,
      "relax_warning": true
    },
    {
      "temperature": 515.0,
      "n_eff": 11.0,
      "tau_int_steps": 0.5,
      "relax_warning": false
    },
    {
      "temperature": 520.0,
      "n_eff": 7.0,
      "tau_int_steps": 0.5,
      "relax_warning": false
    },
    {
      "temperature": 520.0,
      "n_eff": 3.0,
      "tau_int_steps": 0.5,
      "relax_warning": true
    },
    {
      "temperature": 520.0,
      "n_eff": 3.12,
      "tau_int_steps": 1.4,
      "relax_warning": true
    },
    {
      "temperature": 500.0,
      "n_eff": 5.0,
      "tau_int_steps": 0.5,
      "relax_warning": false
    },
    {
      "temperature": 500.0,
      "n_eff": 22.21,
      "tau_int_steps": 0.5,
      "relax_warning": false
    },
    {
      "temperature": 495.0,
      "n_eff": 4.0,
      "tau_int_steps": 0.5,
      "relax_warning": true
    },
    {
      "temperature": 480.0,
      "n_eff": 19.78,
      "tau_int_steps": 0.8,
      "relax_warning": false
    },
    {
      "temperature": 455.0,
      "n_eff": 6.0,
      "tau_int_steps": 0.5,
      "relax_warning": false
    },
    {
      "temperature": 460.0,
      "n_eff": 13.0,
      "tau_int_steps": 0.5,
      "relax_warning": false
    },
    {
      "temperature": 455.0,
      "n_eff": 11.0,
      "tau_int_steps": 0.5,
      "relax_warning": false
    },
    {
      "temperature": 460.0,
      "n_eff": 3.0,
      "tau_int_steps": 0.5,
      "relax_warning": true
    },
    {
      "temperature": 435.0,
      "n_eff": 11.0,
      "tau_int_steps": 0.5,
      "relax_warning": false
    },
    {
      "temperature": 420.0,
      "n_eff": 55.0,
      "tau_int_steps": 0.5,
      "relax_warning": false
    },
    {
      "temperature": 400.0,
      "n_eff": 13.0,
      "tau_int_steps": 0.5,
      "relax_warning": false
    },
    {
      "temperature": 380.0,
      "n_eff": 49.0,
      "tau_int_steps": 0.5,
      "relax_warning": false
    },
    {
      "temperature": 375.0,
      "n_eff": 3.0,
      "tau_int_steps": 0.5,
      "relax_warning": true
    },
    {
      "temperature": 365.0,
      "n_eff": 8.0,
      "tau_int_steps": 0.5,
      "relax_warning": false
    },
    {
      "temperature": 360.0,
      "n_eff": 18.0,
      "tau_int_steps": 0.5,
      "relax_warning": false
    },
    {
      "temperature": 340.0,
      "n_eff": 40.0,
      "tau_int_steps": 0.5,
      "relax_warning": false
    },
    {
      "temperature": 300.0,
      "n_eff": 21.45,
      "tau_int_steps": 1.5,
      "relax_warning": false
    },
    {
      "temperature": 275.0,
      "n_eff": 6.19,
      "tau_int_steps": 3.2,
      "relax_warning": false
    },
    {
      "temperature": 260.0,
      "n_eff": 25.0,
      "tau_int_steps": 0.5,
      "relax_warning": false
    },
    {
      "temperature": 240.0,
      "n_eff": 33.0,
      "tau_int_steps": 0.5,
      "relax_warning": false
    },
    {
      "temperature": 220.0,
      "n_eff": 32.0,
      "tau_int_steps": 0.5,
      "relax_warning": false
    }
  ],
  "cte_glassy_per_K": 0.00022503,
  "cte_rubbery_per_K": 0.000303322,
  "dCp_status": "success",
  "dCp_J_per_g_K": 0.2542,
  "H_slope_glassy_kcal_per_mol_K": 27.2751,
  "H_slope_rubbery_kcal_per_mol_K": 29.4654,
  "H_r_squared": 0.9875,
  "H_fit_quality": "GOOD",
  "system_mass_g_per_mol": 36052.22,
  "tg_fit_png": "/home/arz2/PolyJarvis/data/PLA1/graphs/tg_r640/tg_fit.png"
}